{
  "version": "3.6.16",
  "flags": {},
  "shapes": [
    {
      "label": "weizen",
      "line_color": null,
      "fill_color": null,
      "points": [
        [
          3254,
          1742
        ],
        [
          3038,
          1871
        ]
      ],
      "shape_type": "rectangle"
    },
    {
      "label": "weizen",
      "line_color": null,
      "fill_color": null,
      "points": [
        [
          3059,
          2387
        ],
        [
          3309,
          2492
        ]
      ],
      "shape_type": "rectangle"
    },
    {
      "label": "weizen",
      "line_color": null,
      "fill_color": null,
      "points": [
        [
          3950,
          2292
        ],
        [
          4121,
          2112
        ]
      ],
      "shape_type": "rectangle"
    },
    {
      "label": "weizen",
      "line_color": null,
      "fill_color": null,
      "points": [
        [
          4671,
          1850
        ],
        [
          4871,
          2071
        ]
      ],
      "shape_type": "rectangle"
    },
    {
      "label": "weizen",
      "line_color": null,
      "fill_color": null,
      "points": [
        [
          3825,
          3692
        ],
        [
          4025,
          3537
        ]
      ],
      "shape_type": "rectangle"
    },
    {
      "label": "weizen",
      "line_color": null,
      "fill_color": null,
      "points": [
        [
          3971,
          1042
        ],
        [
          4071,
          854
        ]
      ],
      "shape_type": "rectangle"
    },
    {
      "label": "weizen",
      "line_color": null,
      "fill_color": null,
      "points": [
        [
          2629,
          1196
        ],
        [
          2879,
          1079
        ]
      ],
      "shape_type": "rectangle"
    },
    {
      "label": "weizen",
      "line_color": null,
      "fill_color": null,
      "points": [
        [
          684,
          1396
        ],
        [
          934,
          1242
        ]
      ],
      "shape_type": "rectangle"
    },
    {
      "label": "weizen",
      "line_color": null,
      "fill_color": null,
      "points": [
        [
          1688,
          212
        ],
        [
          1904,
          67
        ]
      ],
      "shape_type": "rectangle"
    },
    {
      "label": "weizen",
      "line_color": null,
      "fill_color": null,
      "points": [
        [
          3379,
          1067
        ],
        [
          3613,
          1187
        ]
      ],
      "shape_type": "rectangle"
    },
    {
      "label": "weizen",
      "line_color": null,
      "fill_color": null,
      "points": [
        [
          2704,
          1512
        ],
        [
          2971,
          1408
        ]
      ],
      "shape_type": "rectangle"
    },
    {
      "label": "weizen",
      "line_color": null,
      "fill_color": null,
      "points": [
        [
          3404,
          3779
        ],
        [
          3529,
          3583
        ]
      ],
      "shape_type": "rectangle"
    },
    {
      "label": "weizen",
      "line_color": null,
      "fill_color": null,
      "points": [
        [
          75,
          1754
        ],
        [
          238,
          1525
        ]
      ],
      "shape_type": "rectangle"
    },
    {
      "label": "weizen",
      "line_color": null,
      "fill_color": null,
      "points": [
        [
          1417,
          2012
        ],
        [
          1596,
          2187
        ]
      ],
      "shape_type": "rectangle"
    },
    {
      "label": "weizen",
      "line_color": null,
      "fill_color": null,
      "points": [
        [
          3734,
          975
        ],
        [
          3917,
          792
        ]
      ],
      "shape_type": "rectangle"
    },
    {
      "label": "weizen",
      "line_color": null,
      "fill_color": null,
      "points": [
        [
          2904,
          1250
        ],
        [
          3146,
          1154
        ]
      ],
      "shape_type": "rectangle"
    },
    {
      "label": "weizen",
      "line_color": null,
      "fill_color": null,
      "points": [
        [
          3584,
          321
        ],
        [
          3738,
          204
        ]
      ],
      "shape_type": "rectangle"
    }
  ],
  "lineColor": [
    0,
    255,
    0,
    128
  ],
  "fillColor": [
    255,
    0,
    0,
    128
  ],
  "imagePath": "..\\DSC_0991.JPG",
  "imageData": null,
  "imageHeight": 4016,
  "imageWidth": 6016
}