{
  "version": "3.6.16",
  "flags": {},
  "shapes": [
    {
      "label": "weizen",
      "line_color": null,
      "fill_color": null,
      "points": [
        [
          2154,
          1100
        ],
        [
          2313,
          1296
        ]
      ],
      "shape_type": "rectangle"
    },
    {
      "label": "weizen",
      "line_color": null,
      "fill_color": null,
      "points": [
        [
          2041,
          2407
        ],
        [
          1924,
          2624
        ]
      ],
      "shape_type": "rectangle"
    },
    {
      "label": "weizen",
      "line_color": null,
      "fill_color": null,
      "points": [
        [
          2807,
          2817
        ],
        [
          2578,
          2963
        ]
      ],
      "shape_type": "rectangle"
    },
    {
      "label": "weizen",
      "line_color": null,
      "fill_color": null,
      "points": [
        [
          5243,
          2624
        ],
        [
          5148,
          2820
        ]
      ],
      "shape_type": "rectangle"
    },
    {
      "label": "weizen",
      "line_color": null,
      "fill_color": null,
      "points": [
        [
          5367,
          2685
        ],
        [
          5515,
          2880
        ]
      ],
      "shape_type": "rectangle"
    }
  ],
  "lineColor": [
    0,
    255,
    0,
    128
  ],
  "fillColor": [
    255,
    0,
    0,
    128
  ],
  "imagePath": "DSC_1017.JPG",
  "imageData": null,
  "imageHeight": 4016,
  "imageWidth": 6016
}