{
	"version": "3.6.16",
	"flags": {},
	"shapes": [
		{
			"label": "roggen",
			"line_color": null,
			"fill_color": null,
			"points": [
				[
					2654,
					1458
				],
				[
					2875,
					1254
				]
			],
			"shape_type": "rectangle"
		},
		{
			"label": "roggen",
			"line_color": null,
			"fill_color": null,
			"points": [
				[
					6013,
					1758
				],
				[
					5788,
					1962
				]
			],
			"shape_type": "rectangle"
		},
		{
			"label": "roggen",
			"line_color": null,
			"fill_color": null,
			"points": [
				[
					2738,
					2992
				],
				[
					2867,
					3275
				]
			],
			"shape_type": "rectangle"
		},
		{
			"label": "roggen",
			"line_color": null,
			"fill_color": null,
			"points": [
				[
					1792,
					3412
				],
				[
					1975,
					3167
				]
			],
			"shape_type": "rectangle"
		},
		{
			"label": "roggen",
			"line_color": null,
			"fill_color": null,
			"points": [
				[
					2638,
					262
				],
				[
					2792,
					525
				]
			],
			"shape_type": "rectangle"
		},
		{
			"label": "roggen",
			"line_color": null,
			"fill_color": null,
			"points": [
				[
					2388,
					1396
				],
				[
					2509,
					1167
				]
			],
			"shape_type": "rectangle"
		},
		{
			"label": "roggen",
			"line_color": null,
			"fill_color": null,
			"points": [
				[
					4371,
					1612
				],
				[
					4563,
					1392
				]
			],
			"shape_type": "rectangle"
		}
	],
	"lineColor": [
		0,
		255,
		0,
		128
	],
	"fillColor": [
		255,
		0,
		0,
		128
	],
	"imagePath": "DSC_1059.JPG",
	"imageData": null,
	"imageHeight": 4016,
	"imageWidth": 6016
}